universal_mcp/applications/BEST_PRACTICES.md
universal_mcp/applications/ahrefs/README.md
universal_mcp/applications/ahrefs/__init__.py
universal_mcp/applications/ahrefs/app.py
universal_mcp/applications/airtable/README.md
universal_mcp/applications/airtable/__init__.py
universal_mcp/applications/airtable/app.py
universal_mcp/applications/apollo/README.md
universal_mcp/applications/apollo/__init__.py
universal_mcp/applications/apollo/app.py
universal_mcp/applications/asana/README.md
universal_mcp/applications/asana/__init__.py
universal_mcp/applications/asana/app.py
universal_mcp/applications/aws_s3/README.md
universal_mcp/applications/aws_s3/__init__.py
universal_mcp/applications/aws_s3/app.py
universal_mcp/applications/bill/README.md
universal_mcp/applications/bill/__init__.py
universal_mcp/applications/bill/app.py
universal_mcp/applications/box/README.md
universal_mcp/applications/box/__init__.py
universal_mcp/applications/box/app.py
universal_mcp/applications/braze/README.md
universal_mcp/applications/braze/__init__.py
universal_mcp/applications/braze/app.py
universal_mcp/applications/browser_use/README.md
universal_mcp/applications/browser_use/__init__.py
universal_mcp/applications/browser_use/app.py
universal_mcp/applications/cal_com_v2/README.md
universal_mcp/applications/cal_com_v2/__init__.py
universal_mcp/applications/cal_com_v2/app.py
universal_mcp/applications/calendly/README.md
universal_mcp/applications/calendly/__init__.py
universal_mcp/applications/calendly/app.py
universal_mcp/applications/canva/README.md
universal_mcp/applications/canva/__init__.py
universal_mcp/applications/canva/app.py
universal_mcp/applications/clickup/README.md
universal_mcp/applications/clickup/__init__.py
universal_mcp/applications/clickup/app.py
universal_mcp/applications/coda/README.md
universal_mcp/applications/coda/__init__.py
universal_mcp/applications/coda/app.py
universal_mcp/applications/confluence/README.md
universal_mcp/applications/confluence/__init__.py
universal_mcp_applications-0.1.36.dist-info/METADATA
universal_mcp_applications-0.1.36.dist-info/WHEEL
universal_mcp_applications-0.1.36.dist-info/licenses/LICENSE
universal_mcp_applications-0.1.36.dist-info/RECORD
